gpi_core/__init__.py
gpi_core/display/__init__.py
gpi_core/display/GPI/CrossSection_GPI.py
gpi_core/display/GPI/DataQuery_GPI.py
gpi_core/display/GPI/DisplayMacro_GPI.net
gpi_core/display/GPI/GLViewer_GPI.py
gpi_core/display/GPI/ImageCompare_GPI.py
gpi_core/display/GPI/ImageDisplay_GPI.py
gpi_core/display/GPI/ImageRate_GPI.py
gpi_core/display/GPI/ImageViewer.md
gpi_core/display/GPI/ImageViewer_GPI.py
gpi_core/display/GPI/Matplotlib_GPI.py
gpi_core/display/GPI/dictionquery_GPI.py
gpi_core/display/GPI/__pycache__/CrossSection_GPI.cpython-39.pyc
gpi_core/display/GPI/__pycache__/DataQuery_GPI.cpython-39.pyc
gpi_core/display/GPI/__pycache__/GLViewer_GPI.cpython-39.pyc
gpi_core/display/GPI/__pycache__/ImageCompare_GPI.cpython-39.pyc
gpi_core/display/GPI/__pycache__/ImageDisplay_GPI.cpython-39.pyc
gpi_core/display/GPI/__pycache__/ImageRate_GPI.cpython-39.pyc
gpi_core/display/GPI/__pycache__/ImageViewer_GPI.cpython-39.pyc
gpi_core/display/GPI/__pycache__/Matplotlib_GPI.cpython-39.pyc
gpi_core/display/GPI/__pycache__/dictionquery_GPI.cpython-39.pyc
gpi_core/fileIO/DownloadFile_GPI.py
gpi_core/fileIO/__init__.py
gpi_core/fileIO/dicomlib.py
gpi_core/fileIO/GPI/Audio_GPI.py
gpi_core/fileIO/GPI/DICOMheader_GPI.py
gpi_core/fileIO/GPI/DownloadFile_GPI.py
gpi_core/fileIO/GPI/ReadCSV_GPI.py
gpi_core/fileIO/GPI/ReadDICOM_GPI.py
gpi_core/fileIO/GPI/ReadHDF5_GPI.py
gpi_core/fileIO/GPI/ReadImage_GPI.py
gpi_core/fileIO/GPI/ReadMatlab_GPI.py
gpi_core/fileIO/GPI/ReadNPY_GPI.py
gpi_core/fileIO/GPI/ReadPickled_GPI.py
gpi_core/fileIO/GPI/ReadRaw_GPI.py
gpi_core/fileIO/GPI/WriteCSV_GPI.py
gpi_core/fileIO/GPI/WriteHDF5_GPI.py
gpi_core/fileIO/GPI/WriteImage_GPI.py
gpi_core/fileIO/GPI/WriteNPY_GPI.py
gpi_core/fileIO/GPI/WritePickled_GPI.py
gpi_core/fileIO/GPI/WriteRaw_GPI.py
gpi_core/fileIO/GPI/__pycache__/Audio_GPI.cpython-39.pyc
gpi_core/fileIO/GPI/__pycache__/DICOMheader_GPI.cpython-39.pyc
gpi_core/fileIO/GPI/__pycache__/DownloadFile_GPI.cpython-39.pyc
gpi_core-2.4.0.dist-info/AUTHORS
gpi_core-2.4.0.dist-info/COPYING
gpi_core-2.4.0.dist-info/COPYING.LESSER
gpi_core-2.4.0.dist-info/LICENSE
gpi_core-2.4.0.dist-info/METADATA
gpi_core-2.4.0.dist-info/WHEEL
gpi_core-2.4.0.dist-info/top_level.txt
gpi_core-2.4.0.dist-info/RECORD
