Metadata-Version: 2.1
Name: gpi_core
Version: 2.4.0
Summary: Graphical Programming Interface
Home-page: https://github.com/gpilab/framework
Author: AbdulRahman Alfayad
Author-email: alfayad.abdulrahman@mayo.edu
License: GNU
Platform: UNKNOWN
Requires-Python: >=3.7
License-File: LICENSE
License-File: COPYING
License-File: COPYING.LESSER
License-File: AUTHORS
